odoo/addons/l10n_hr_bank/README.rst
odoo/addons/l10n_hr_bank/__init__.py
odoo/addons/l10n_hr_bank/__manifest__.py
odoo/addons/l10n_hr_bank/data/res_bank_data.xml
odoo/addons/l10n_hr_bank/i18n/l10n_hr_bank.pot
odoo/addons/l10n_hr_bank/static/description/icon.png
odoo_addon_l10n_hr_bank-16.0.1.0.1.dist-info/METADATA
odoo_addon_l10n_hr_bank-16.0.1.0.1.dist-info/WHEEL
odoo_addon_l10n_hr_bank-16.0.1.0.1.dist-info/top_level.txt
odoo_addon_l10n_hr_bank-16.0.1.0.1.dist-info/RECORD
